EduKit/__init__.py
EduKit/edukit.py
EduKit-0.0.3.dist-info/LICENSE
EduKit-0.0.3.dist-info/METADATA
EduKit-0.0.3.dist-info/WHEEL
EduKit-0.0.3.dist-info/top_level.txt
EduKit-0.0.3.dist-info/RECORD
