Metadata-Version: 2.1
Name: EduKit
Version: 0.0.3
Summary: Library for teaching Python to students
Home-page: https://github.com/lill74/EduKit
Author: Lee Soul
Author-email: a010393223@gmail.com
License: UNKNOWN
Platform: UNKNOWN
Classifier: Programming Language :: Python :: 3
Classifier: License :: OSI Approved :: MIT License
Classifier: Operating System :: OS Independent
Requires-Python: >=3.6
Requires-Dist: requests (==2.24.0)
Requires-Dist: beautifulsoup4 (==4.9.1)
Requires-Dist: konlpy (==0.5.2)
Requires-Dist: matplotlib (==3.3.0)
